README.txt
setup.py
screencastwriter.egg-info/PKG-INFO
screencastwriter.egg-info/SOURCES.txt
screencastwriter.egg-info/top_level.txt
src/scw
src/screencastwriter/__init__.py
src/screencastwriter/scw.py
src/screencastwriter/scw.glade
src/screencastwriter/testcast.txt