Metadata-Version: 1.0
Name: screencastwriter
Version: 0.1
Summary: Screencast Writer is screencast helper tool
Home-page: http://zissue.berlios.de/tools/scw/
Author: Baiju M
Author-email: baiju.m.mail@gmail.com
License: GPL v2
Download-URL: http://zissue.berlios.de/tools/scw-0.1.0.tar.bz2
Platform: UNKNOWN
Classifier: Programming Language :: Python
Classifier: License :: OSI Approved :: GNU General Public License (GPL)
Classifier: Natural Language :: English
Classifier: Development Status :: 3 - Alpha
Classifier: Operating System :: POSIX
Classifier: Environment :: X11 Applications
Classifier: Intended Audience :: Developers
Classifier: Topic :: Desktop Environment
Classifier: Topic :: Software Development
